lino_react/__init__.py
lino_react/react/__init__.py
lino_react/react/icons.py
lino_react/react/index.js
lino_react/react/models.py
lino_react/react/renderer.py
lino_react/react/sphinxconf.py
lino_react/react/views.py
lino_react/react/components/ActionHandler.tsx
lino_react/react/components/App.css
lino_react/react/components/App.jsx
lino_react/react/components/AppCSS.js
lino_react/react/components/AppInlineProfile.jsx
lino_react/react/components/AppMenu.css
lino_react/react/components/AppMenu.jsx
lino_react/react/components/AppTopBar.css
lino_react/react/components/AppTopbar.jsx
lino_react/react/components/AutoComplete.tsx
lino_react/react/components/Base.ts
lino_react/react/components/DashboardItems.jsx
lino_react/react/components/DataProvider.jsx
lino_react/react/components/ForeignKeyElement.jsx
lino_react/react/components/GridElement.css
lino_react/react/components/GridElement.jsx
lino_react/react/components/LinoBbar.css
lino_react/react/components/LinoBbar.jsx
lino_react/react/components/LinoBody.css
lino_react/react/components/LinoBody.jsx
lino_react/react/components/LinoComponentUtils.jsx
lino_react/react/components/LinoComponents.css
lino_react/react/components/LinoComponents.jsx
lino_react/react/components/LinoDataView.css
lino_react/react/components/LinoDataView.jsx
lino_react/react/components/LinoDetail.jsx
lino_react/react/components/LinoDialog.jsx
lino_react/react/components/LinoEditor.jsx
lino_react/react/components/LinoPaginator.jsx
lino_react/react/components/LinoParamsPanel.jsx
lino_react/react/components/LinoToolbar.css
lino_react/react/components/LinoToolbar.jsx
lino_react/react/components/LinoUtils.js
lino_react/react/components/LinoWebCam.tsx
lino_react/react/components/LoadingMask.jsx
lino_react/react/components/NavigationControl.js
lino_react/react/components/SiteContext.jsx
lino_react/react/components/TextFieldElement.css
lino_react/react/components/TextFieldElement.jsx
lino_react/react/components/ToolbarComponents.tsx
lino_react-26.1.5.dist-info/METADATA
lino_react-26.1.5.dist-info/WHEEL
lino_react-26.1.5.dist-info/licenses/COPYING
lino_react-26.1.5.dist-info/RECORD
