Metadata-Version: 2.4
Name: lino_react
Version: 26.1.5
Summary: The React front end for Lino
Project-URL: Homepage, https://react.lino-framework.org
Project-URL: Repository, https://gitlab.com/lino-framework/react
Author-email: Rumma & Ko Ltd <info@saffre-rumma.net>, Luc Saffre <luc@saffre-rumma.net>
License:                     GNU AFFERO GENERAL PUBLIC LICENSE
License-File: COPYING
Keywords: Django,React,customized,framework
Classifier: Development Status :: 5 - Production/Stable
Classifier: Environment :: Web Environment
Classifier: Framework :: Django
Classifier: Intended Audience :: Developers
Classifier: Intended Audience :: System Administrators
Classifier: License :: OSI Approved :: GNU Affero General Public License v3
Classifier: Natural Language :: English
Classifier: Natural Language :: French
Classifier: Natural Language :: German
Classifier: Operating System :: OS Independent
Classifier: Programming Language :: Python
Classifier: Programming Language :: Python :: 3
Classifier: Topic :: Database :: Front-Ends
Classifier: Topic :: Office/Business
Classifier: Topic :: Software Development :: Libraries :: Application Frameworks
Requires-Python: >=3.8
Requires-Dist: deepmerge
Requires-Dist: lino
Provides-Extra: testing
Requires-Dist: atelier; extra == 'testing'
Requires-Dist: hatch; extra == 'testing'
Requires-Dist: pytest; extra == 'testing'
Requires-Dist: pytest-cov; extra == 'testing'
Requires-Dist: pytest-env; extra == 'testing'
Requires-Dist: pytest-forked; extra == 'testing'
Requires-Dist: pytest-html; extra == 'testing'
